musenet_midi_py/__init__.py
musenet_midi_py/main.py
musenet_midi_py-0.1.1.dist-info/WHEEL
musenet_midi_py-0.1.1.dist-info/METADATA
musenet_midi_py-0.1.1.dist-info/RECORD
