Metadata-Version: 2.1
Name: musenet-midi-py
Version: 0.1.1
Summary: MuseNet Midi encoder and decoder
Author: daanklijn
Author-email: daanklijn0@gmail.com
Requires-Python: >=3.7,<4.0
Classifier: Programming Language :: Python :: 3
Classifier: Programming Language :: Python :: 3.7
Classifier: Programming Language :: Python :: 3.8
Classifier: Programming Language :: Python :: 3.9
Requires-Dist: mido (>=1.2.9,<2.0.0)
Requires-Dist: pytest (>=6.1.2,<7.0.0)
